<pkg-contents spec="1.12"><f n="XiphQT.component" o="root" g="admin" p="16877" pt="/Users/tomfinegan/webmquicktime/third_party/xiphqt/XiphQT.component" m="false" t="file"><f n="Contents" o="tomfinegan" g="5000" p="16877"><f n="Info.plist" o="tomfinegan" g="5000" p="33188"/><f n="MacOS" o="tomfinegan" g="5000" p="16877"><f n="XiphQT" o="tomfinegan" g="5000" p="33261"/></f><f n="Resources" o="tomfinegan" g="5000" p="16877"><f n="English.lproj" o="tomfinegan" g="5000" p="16877"><f n="InfoPlist.strings" o="tomfinegan" g="5000" p="33188"/></f><f n="MetaDataConfig.plist" o="tomfinegan" g="5000" p="33188"/><f n="OggExport.nib" o="tomfinegan" g="5000" p="16877"><f n="classes.nib" o="tomfinegan" g="5000" p="33188"/><f n="info.nib" o="tomfinegan" g="5000" p="33188"/><f n="objects.xib" o="tomfinegan" g="5000" p="33188"/></f><f n="XiphQT.rsrc" o="tomfinegan" g="5000" p="33188"/></f></f><f n="Icon " o="tomfinegan" g="5000" p="33188"/><mod>group</mod><mod>owner</mod></f></pkg-contents>